yousearch/__init__.py
yousearch/__main__.py
yousearch/cli.py
yousearch/config.py
yousearch/mpv_api.py
yousearch/youtube_api.py
yousearch-0.1.6.dist-info/entry_points.txt
yousearch-0.1.6.dist-info/LICENSE
yousearch-0.1.6.dist-info/WHEEL
yousearch-0.1.6.dist-info/METADATA
yousearch-0.1.6.dist-info/RECORD
