Metadata-Version: 2.1
Name: yousearch
Version: 0.1.6
Summary: Interactive CLI to fetch and browse transcripts of YouTube videos
Home-page: https://github.com/buecheko/YouSearch
Author: Konstantin
Author-email: buecheko@protonmail.ch
Requires-Python: >=3.8,<4.0
Classifier: Programming Language :: Python :: 3
Classifier: Programming Language :: Python :: 3.8
Requires-Dist: bs4 (>=0.0.1,<0.0.2)
Requires-Dist: youtube_transcript_api (>=0.3.0,<0.4.0)
Project-URL: Repository, https://github.com/buecheko/YouSearch
